XXProgram/__init__.py
XXProgram/programs.py
xxprogram-1.1.2.dist-info/METADATA
xxprogram-1.1.2.dist-info/RECORD
xxprogram-1.1.2.dist-info/WHEEL
xxprogram-1.1.2.dist-info/top_level.txt
