Metadata-Version: 2.1
Name: xxprogram
Version: 1.1.2
Summary: 用程序员梗随机生成用户名，娱乐项目
Home-page: https://github.com/zhonlaoda/xxprogram
Author: ZRui
Author-email: a1571093237@msn.cn
License: UNKNOWN
Platform: UNKNOWN
Classifier: Programming Language :: Python :: 3
Classifier: License :: OSI Approved :: Apache Software License
Classifier: Operating System :: OS Independent
